<?xml version="1.0" encoding="UTF-8"?>
<Defs>
  <ThingDef ParentName = "Building_BioBase">
<!--Setup-->
    <defName>BIO_TestWall</defName>
    <label>Test Wall</label>
    <description>Just a test.</description>
<!--Graphics & Effects-->
    <graphicData>
      <texPath>Things/Building/TestWall</texPath>
      <graphicClass>Graphic_Single</graphicClass>
      <linkType>CornerFiller</linkType>
      <linkFlags>
        <li>Wall</li>
        <li>Rock</li>
      </linkFlags>
    </graphicData>
    <uiIconPath>Things/Building/TestWall</uiIconPath>
<!--Thing Properties-->

  </ThingDef>
</Defs>
